ipyreactflow/__init__.py
ipyreactflow/static/color_picker.css
ipyreactflow/static/color_picker.js
ipyreactflow/static/intersecting_nodes.css
ipyreactflow/static/intersecting_nodes.js
ipyreactflow/static/widget.css
ipyreactflow/static/widget.js
ipyreactflow-0.0.7.dist-info/METADATA
ipyreactflow-0.0.7.dist-info/WHEEL
ipyreactflow-0.0.7.dist-info/licenses/LICENSE
ipyreactflow-0.0.7.dist-info/RECORD
