Metadata-Version: 2.3
Name: ipyreactflow
Version: 0.0.7
License-File: LICENSE
Requires-Dist: anywidget
Provides-Extra: dev
Requires-Dist: jupyterlab; extra == 'dev'
Requires-Dist: watchfiles; extra == 'dev'
